{
	"format_version": "1.12.0",
	"minecraft:geometry": [
		{
			"description": {
				"identifier": "geometry.unknown",
				"texture_width": 512,
				"texture_height": 512,
				"visible_bounds_width": 8,
				"visible_bounds_height": 4.5,
				"visible_bounds_offset": [0, 1.75, 0]
			},
			"bones": [
				{
					"name": "Archer",
					"pivot": [0, -10, -12],
					"rotation": [0, 180, 0]
				},
				{
					"name": "hull",
					"parent": "Archer",
					"pivot": [-0.19027, 19.53012, -20.05139],
					"cubes": [
						{"origin": [-18, 12, -46], "size": [35, 5, 72], "uv": [0, 79]},
						{"origin": [-18, 14.72387, 12.39055], "size": [35, 6, 13], "pivot": [0, 18.22387, 18.89055], "rotation": [-35, 0, 0], "uv": [113, 229]},
						{"origin": [-18, 17, -14], "size": [35, 7, 29], "uv": [0, 232]},
						{"origin": [-15, 18, 15], "size": [29, 6, 8], "uv": [232, 136]},
						{"origin": [-56, 17, -32], "size": [18, 4, 7], "pivot": [-24, 21, 16], "rotation": [0, -90, 0], "uv": [143, 23]},
						{"origin": [-56, 17, 10], "size": [18, 4, 7], "pivot": [-24, 21, 16], "rotation": [0, -90, 0], "uv": [142, 139]},
						{"origin": [-76, 17, -27], "size": [18, 4, 4], "pivot": [-24, 21, 16], "rotation": [0, -90, 0], "uv": [0, 63]},
						{"origin": [-76, 17, 7], "size": [20, 5, 10], "pivot": [-24, 21, 16], "rotation": [0, -90, 0], "uv": [0, 37]},
						{"origin": [-17, 12, -55], "size": [3, 3, 4], "uv": [143, 41]},
						{"origin": [13, 12, -55], "size": [3, 3, 4], "uv": [143, 34]},
						{"origin": [-13, 17, -38], "size": [6, 10, 13], "uv": [143, 0]},
						{"origin": [-74, 17, -21], "size": [10, 8, 5], "pivot": [-24, 21, 16], "rotation": [0, -90, 0], "uv": [168, 0]},
						{"origin": [-71, 31, -21], "size": [8, 6, 3], "pivot": [-24, 21, 16], "rotation": [0, -90, 0], "uv": [50, 37]},
						{"origin": [-54.75736, 16.93226, -32.7654], "size": [9, 13, 3], "pivot": [-24.75736, 37.93226, 7.2346], "rotation": [0, -90, 0], "uv": [186, 13]},
						{"origin": [-54.75736, 16.93226, -4.7654], "size": [9, 13, 3], "pivot": [-24.75736, 37.93226, 7.2346], "rotation": [0, -90, 0], "uv": [0, 183]},
						{"origin": [-18, 6, -55], "size": [35, 6, 73], "uv": [0, 0]},
						{"origin": [-18, 9.344, 15.57624], "size": [35, 5, 10], "pivot": [0, 11.344, 21.57624], "rotation": [35, 0, 0], "uv": [232, 121]},
						{"origin": [-11.5, 8.39312, -45.94899], "size": [22.5, 32, 5], "pivot": [-7, 29.39312, -43.94899], "rotation": [-22.5, 0, 0], "uv": [0, 0]},
						{"origin": [-3.5, 12.39312, -46.94899], "size": [6.5, 15, 1], "pivot": [-7, 29.39312, -43.94899], "rotation": [-22.5, 0, 0], "uv": [58, 52]},
						{"origin": [-24.25736, 11.93226, -64.26539], "size": [21, 24, 3], "pivot": [-13.25736, 11.93226, -35.76539], "rotation": [-89.99999, -67.5, 89.99999], "uv": [0, 106]},
						{"origin": [-24.25736, 11.93226, -36.26539], "size": [21, 24, 3], "pivot": [-13.25736, 11.93226, -35.76539], "rotation": [-89.99999, -67.5, 89.99999], "uv": [0, 79]},
						{"origin": [12.74264, 29.93226, -37.2654], "size": [23, 8, 3], "pivot": [13.74264, 11.93226, -35.7654], "rotation": [0, -90, 0], "uv": [0, 133]},
						{"origin": [12.74264, 29.93226, -9.2654], "size": [23, 8, 3], "pivot": [13.74264, 11.93226, -35.7654], "rotation": [0, -90, 0], "uv": [0, 52]},
						{"origin": [-15.57538, 9.86259, -44.96384], "size": [6, 30, 3], "pivot": [-12.57538, 24.86259, -43.46384], "rotation": [-30.36119, 40.78947, -20.94102], "uv": [48, 79]},
						{"origin": [9.06066, 9.86259, -44.96384], "size": [6, 30, 3], "pivot": [12.06066, 24.86259, -43.46384], "rotation": [-149.63881, 40.78947, -159.05898], "uv": [54, 0]},
						{"origin": [17, 16, -51], "size": [8, 1, 73], "uv": [143, 6]},
						{"origin": [17, 12, -54], "size": [0, 4, 8], "uv": [23, 136]},
						{"origin": [-18, 12, -54], "size": [0, 4, 8], "uv": [54, 25]},
						{"origin": [-26, 16, -51], "size": [8, 1, 73], "uv": [141, 83]},
						{"origin": [-26, 14.65648, -55.26109], "size": [8, 1, 5], "pivot": [-21, 15.15648, -52.76109], "rotation": [35, 0, 0], "uv": [185, 139]},
						{"origin": [-26, 14.65648, 21.26109], "size": [8, 1, 5], "pivot": [-21.5, 15.15648, 23.76109], "rotation": [145, 0, 0], "uv": [0, 144]},
						{"origin": [17, 14.65648, 21.26109], "size": [8, 1, 5], "pivot": [-21.5, 15.15648, 23.76109], "rotation": [145, 0, 0], "uv": [143, 64]},
						{"origin": [17, 14.65648, -55.26109], "size": [8, 1, 5], "pivot": [-21, 15.15648, -52.76109], "rotation": [35, 0, 0], "uv": [166, 65]},
						{"origin": [-1.03777, 17, -12.74648], "size": [13.71, 23, 5], "pivot": [5.67223, 28.5, -10.24648], "rotation": [0, 10, 0], "uv": [142, 111]},
						{"origin": [-13.66782, 17, -12.79684], "size": [13.71, 23, 5], "pivot": [-6.95782, 28.5, -10.29684], "rotation": [0, -10, 0], "uv": [142, 83]},
						{"origin": [7.6521, 24, -15.69323], "size": [5, 16, 5], "pivot": [12.6521, 28.5, -17.19323], "rotation": [0, 40, 0], "uv": [30, 172]},
						{"origin": [-13.09962, 24, -32.52622], "size": [5, 16, 5], "pivot": [11.90038, 28.5, -17.02622], "rotation": [0, 40, 0], "uv": [48, 112]}
					]
				},
				{
					"name": "gun",
					"parent": "Archer",
					"pivot": [0, -10, -12],
					"cubes": [
						{"origin": [-2, 31, -1], "size": [3, 3, 35], "uv": [232, 83]},
						{"origin": [-3, 30, 34], "size": [5, 5, 7], "uv": [85, 196]},
						{"origin": [-3, 30, -9], "size": [5, 5, 8], "uv": [85, 183]},
						{"origin": [-3, 30, -21], "size": [5, 6, 10], "uv": [42, 134]},
						{"origin": [-3, 30, -27], "size": [5, 3, 6], "uv": [187, 44]}
					]
				},
				{
					"name": "tracks",
					"parent": "Archer",
					"pivot": [0, -10, -12],
					"cubes": [
						{"origin": [18, 14, -51], "size": [7, 1, 71.7], "uv": [85, 157]},
						{"origin": [-26, 14, -51], "size": [7, 1, 71.7], "uv": [0, 156]},
						{"origin": [-26, 0, -39], "size": [7, 1, 50], "uv": [191, 208]},
						{"origin": [18, 0, -39], "size": [7, 1, 50], "uv": [170, 157]},
						{"origin": [18, 1.3181, 8.47533], "size": [7, 1, 12], "pivot": [21.5, 7.8181, 13.47533], "rotation": [20, 0, 0], "uv": [85, 156]},
						{"origin": [18, 1.78109, -52.57195], "size": [7, 1, 14], "pivot": [21.5, 2.28109, -44.57195], "rotation": [-17.5, 0, 0], "uv": [143, 49]},
						{"origin": [-26, 1.78109, -52.57195], "size": [7, 1, 14], "pivot": [21.5, 2.28109, -44.57195], "rotation": [-17.5, 0, 0], "uv": [143, 34]},
						{"origin": [-26, 1.3181, 8.47533], "size": [7, 1, 12], "pivot": [21.5, 7.8181, 13.47533], "rotation": [20, 0, 0], "uv": [0, 156]},
						{"origin": [18, 4.60424, 10.77631], "size": [7, 1, 9], "pivot": [21.5, 10.10424, 16.77631], "rotation": [90, 0, 0], "uv": [171, 34]},
						{"origin": [18, 78.70988, 11.14796], "size": [7, 1, 9], "pivot": [21.5, 10.20988, 17.14796], "rotation": [90, 0, 0], "uv": [170, 157]},
						{"origin": [-26, 78.70988, 11.14796], "size": [7, 1, 9], "pivot": [21.5, 10.20988, 17.14796], "rotation": [90, 0, 0], "uv": [35, 63]},
						{"origin": [18, 13.04889, 20.2505], "size": [7, 1, 2.4], "pivot": [21.5, 13.54889, 21.2505], "rotation": [130, 0, 0], "uv": [190, 148]},
						{"origin": [-26, 13.04889, 20.2505], "size": [7, 1, 2.4], "pivot": [21.5, 13.54889, 21.2505], "rotation": [130, 0, 0], "uv": [50, 184]},
						{"origin": [-26, 21.52168, -56.22789], "size": [7, 1, 2.4], "pivot": [-22.5, 17.02168, -55.02789], "rotation": [-130, 0, 0], "uv": [26, 148]},
						{"origin": [18, 21.52168, -56.22789], "size": [7, 1, 2.4], "pivot": [-22.5, 17.02168, -55.02789], "rotation": [-130, 0, 0], "uv": [143, 70]},
						{"origin": [-26, 4.60424, 10.77631], "size": [7, 1, 9], "pivot": [21.5, 10.10424, 16.77631], "rotation": [90, 0, 0], "uv": [170, 167]},
						{"origin": [-19, 4, -32], "size": [1, 8, 10], "uv": [170, 177]},
						{"origin": [-19, 4, -6], "size": [1, 8, 10], "uv": [175, 44]},
						{"origin": [17, 4, -6], "size": [1, 8, 10], "uv": [127, 173]},
						{"origin": [17, 4, -32], "size": [1, 8, 10], "uv": [105, 173]}
					]
				},
				{
					"name": "wheels",
					"parent": "Archer",
					"pivot": [0, -10, -12]
				},
				{
					"name": "wheel1",
					"parent": "wheels",
					"pivot": [-22, 9.5, 17],
					"cubes": [
						{"origin": [-26, 6, 13.5], "size": [8, 7, 7], "uv": [0, 169]}
					]
				},
				{
					"name": "wheel2",
					"parent": "wheels",
					"pivot": [-22, 5, 6.5],
					"cubes": [
						{"origin": [-25, 1.5, 3], "size": [6, 7, 7], "uv": [178, 125]}
					]
				},
				{
					"name": "wheel3",
					"parent": "wheels",
					"pivot": [-22, 4.5, -1],
					"cubes": [
						{"origin": [-25, 1.5, -4], "size": [6, 6, 6], "uv": [196, 161]}
					]
				},
				{
					"name": "wheel4",
					"parent": "wheels",
					"pivot": [-22, 4.5, -8],
					"cubes": [
						{"origin": [-25, 1.5, -11], "size": [6, 6, 6], "uv": [192, 177]}
					]
				},
				{
					"name": "wheel5",
					"parent": "wheels",
					"pivot": [-22, 4.5, -20],
					"cubes": [
						{"origin": [-25, 1.5, -23], "size": [6, 6, 6], "uv": [129, 191]}
					]
				},
				{
					"name": "wheel6",
					"parent": "wheels",
					"pivot": [-22, 4.5, -27],
					"cubes": [
						{"origin": [-25, 1.5, -30], "size": [6, 6, 6], "uv": [18, 193]}
					]
				},
				{
					"name": "wheel7",
					"parent": "wheels",
					"pivot": [-22, 5, -34.5],
					"cubes": [
						{"origin": [-25, 1.5, -38], "size": [6, 7, 7], "uv": [178, 111]}
					]
				},
				{
					"name": "wheel8",
					"parent": "wheels",
					"pivot": [-22, 9, -46],
					"cubes": [
						{"origin": [-26, 5, -50], "size": [8, 8, 8], "uv": [123, 157]}
					]
				},
				{
					"name": "wheel9",
					"parent": "wheels",
					"pivot": [-22, 12, -1],
					"cubes": [
						{"origin": [-25, 10, -3], "size": [6, 4, 4], "uv": [111, 156]}
					]
				},
				{
					"name": "wheel10",
					"parent": "wheels",
					"pivot": [-22, 12, -27],
					"cubes": [
						{"origin": [-25, 10, -29], "size": [6, 4, 4], "uv": [26, 156]}
					]
				},
				{
					"name": "wheel11",
					"parent": "wheels",
					"pivot": [21, 9.5, 17],
					"cubes": [
						{"origin": [17, 6, 13.5], "size": [8, 7, 7], "uv": [85, 169]}
					]
				},
				{
					"name": "wheel12",
					"parent": "wheels",
					"pivot": [21, 5, 6.5],
					"cubes": [
						{"origin": [18, 1.5, 3], "size": [6, 7, 7], "uv": [178, 83]}
					]
				},
				{
					"name": "wheel13",
					"parent": "wheels",
					"pivot": [21, 4.5, -1],
					"cubes": [
						{"origin": [18, 1.5, -4], "size": [6, 6, 6], "uv": [44, 187]}
					]
				},
				{
					"name": "wheel14",
					"parent": "wheels",
					"pivot": [21, 4.5, -8],
					"cubes": [
						{"origin": [18, 1.5, -11], "size": [6, 6, 6], "uv": [186, 189]}
					]
				},
				{
					"name": "wheel15",
					"parent": "wheels",
					"pivot": [21, 4.5, -20],
					"cubes": [
						{"origin": [18, 1.5, -23], "size": [6, 6, 6], "uv": [105, 191]}
					]
				},
				{
					"name": "wheel16",
					"parent": "wheels",
					"pivot": [21, 4.5, -27],
					"cubes": [
						{"origin": [18, 1.5, -30], "size": [6, 6, 6], "uv": [191, 56]}
					]
				},
				{
					"name": "wheel17",
					"parent": "wheels",
					"pivot": [21, 5, -34.5],
					"cubes": [
						{"origin": [18, 1.5, -38], "size": [6, 7, 7], "uv": [178, 97]}
					]
				},
				{
					"name": "wheel18",
					"parent": "wheels",
					"pivot": [21, 9, -46],
					"cubes": [
						{"origin": [17, 5, -50], "size": [8, 8, 8], "uv": [38, 156]}
					]
				},
				{
					"name": "wheel19",
					"parent": "wheels",
					"pivot": [21, 12, -1],
					"cubes": [
						{"origin": [18, 10, -3], "size": [6, 4, 4], "uv": [50, 172]}
					]
				},
				{
					"name": "wheel20",
					"parent": "wheels",
					"pivot": [21, 12, -27],
					"cubes": [
						{"origin": [18, 10, -29], "size": [6, 4, 4], "uv": [117, 173]}
					]
				}
			]
		}
	]
}